examples/00_intro_to_plant_data.ipynb
examples/01_utils_examples.ipynb
examples/02a_plant_aep_analysis.ipynb
examples/02b_plant_aep_analysis_cubico.ipynb
examples/02c_augmented_plant_aep_analysis.ipynb
examples/03_turbine_ideal_energy.ipynb
examples/04_electrical_losses.ipynb
examples/05_eya_gap_analysis.ipynb
examples/06_wake_loss_analysis.ipynb
examples/07_static_yaw_misalignment.ipynb
examples/APIKEY
examples/README.md
examples/__init__.py
examples/project_Cubico.py
examples/project_ENGIE.py
examples/data/la_haute_borne.zip
examples/data/plant_meta.json
examples/data/plant_meta.yml
examples/data/readme.md
openoa/__init__.py
openoa/logging.py
openoa/plant.py
openoa/analysis/__init__.py
openoa/analysis/_analysis_validators.py
openoa/analysis/aep.py
openoa/analysis/electrical_losses.py
openoa/analysis/eya_gap_analysis.py
openoa/analysis/turbine_long_term_gross_energy.py
openoa/analysis/wake_losses.py
openoa/analysis/yaw_misalignment.py
openoa/schema/README.md
openoa/schema/__init__.py
openoa/schema/base_electrical_losses_schema.json
openoa/schema/base_electrical_losses_schema.yml
openoa/schema/base_monte_carlo_aep_schema.json
openoa/schema/base_monte_carlo_aep_schema.yml
openoa/schema/base_tie_schema.json
openoa/schema/base_tie_schema.yml
openoa/schema/base_wake_losses_schema.yml
openoa/schema/base_yaw_misalignmental_losses_schema.json
openoa/schema/base_yaw_misalignmental_losses_schema.yml
openoa/schema/full_schema.json
openoa/schema/full_schema.yml
openoa/schema/metadata.py
openoa/schema/scada_wake_losses_schema.json
openoa/schema/scada_wake_losses_schema.yml
openoa/schema/schema.py
openoa/schema/temperature_monte_carlo_aep_schema.json
openoa/schema/temperature_monte_carlo_aep_schema.yml
openoa/schema/temperature_wind_direction_monte_carlo_aep_schema.json
openoa/schema/temperature_wind_direction_monte_carlo_aep_schema.yml
openoa/schema/tower_wake_losses_schema.json
openoa/schema/tower_wake_losses_schema.yml
openoa/schema/wind_direction_monte_carlo_aep_schema.json
openoa-3.1.4.dist-info/licenses/LICENSE.txt
openoa-3.1.4.dist-info/METADATA
openoa-3.1.4.dist-info/WHEEL
openoa-3.1.4.dist-info/top_level.txt
openoa-3.1.4.dist-info/RECORD
