Metadata-Version: 2.4
Name: OpenOA
Version: 3.1.4
Summary: A package for collecting and assigning wind turbine metrics
Author-email: NREL PRUF OA Team <openoa@nrel.gov>
License: BSD 3-Clause License
Project-URL: source, https://github.com/NREL/OpenOA
Project-URL: documentation, https://openoa.readthedocs.io/
Project-URL: issues, https://github.com/NREL/OpenOA/issues
Project-URL: changelog, https://github.com/NREL/OpenOA/blob/main/CHANGELOG.md
Keywords: python3,wind-energy,operations,operational-analysis,operational-assessement,turbine-performance,wind-plant-performance
Classifier: Development Status :: 5 - Production/Stable
Classifier: Intended Audience :: Developers
Classifier: Intended Audience :: Science/Research
Classifier: Intended Audience :: Other Audience
Classifier: License :: OSI Approved :: BSD License
Classifier: Natural Language :: English
Classifier: Operating System :: OS Independent
Classifier: Programming Language :: Python
Classifier: Programming Language :: Python :: 3 :: Only
Classifier: Programming Language :: Python :: 3.10
Classifier: Programming Language :: Python :: 3.11
Classifier: Programming Language :: Python :: 3.12
Classifier: Programming Language :: Python :: 3.13
Classifier: Programming Language :: Python :: 3.14
Classifier: Topic :: Scientific/Engineering
Classifier: Topic :: Software Development :: Libraries :: Python Modules
Classifier: Typing :: Typed
Requires-Python: <3.14,>=3.10
License-File: LICENSE.txt
Requires-Dist: scikit-learn<1.7,>=1.0
Requires-Dist: requests>=2.21.0
Requires-Dist: eia-python>=1.22
Requires-Dist: pyproj>=3.5
Requires-Dist: shapely>=1.8
Requires-Dist: numpy>=1.24
Requires-Dist: pandas<3,>=2.2
Requires-Dist: pygam>=0.11.0
Requires-Dist: scipy>=1.7
Requires-Dist: statsmodels>=0.11; python_version < "3.11"
Requires-Dist: statsmodels>=0.13.3; python_version >= "3.11"
Requires-Dist: tqdm>=4.28.1
Requires-Dist: matplotlib>=3.6
Requires-Dist: bokeh>=3.3
Requires-Dist: attrs>=22.2
Requires-Dist: pytz
Requires-Dist: pyyaml
Requires-Dist: tabulate
Requires-Dist: ipython
Provides-Extra: develop
Requires-Dist: pre-commit; extra == "develop"
Requires-Dist: black; extra == "develop"
Requires-Dist: isort; extra == "develop"
Requires-Dist: flake8; extra == "develop"
Requires-Dist: flake8-docstrings; extra == "develop"
Requires-Dist: pytest>=9; extra == "develop"
Requires-Dist: pytest-cov>=2.8.1; extra == "develop"
Provides-Extra: docs
Requires-Dist: Sphinx!=7.2.0,>=5.0; extra == "docs"
Requires-Dist: pydata-sphinx-theme; extra == "docs"
Requires-Dist: sphinx_design>=0.3; extra == "docs"
Requires-Dist: sphinxcontrib-bibtex; extra == "docs"
Requires-Dist: myst-nb; extra == "docs"
Requires-Dist: myst-parser; extra == "docs"
Provides-Extra: nrel-wind
Requires-Dist: h5pyd; extra == "nrel-wind"
Provides-Extra: reanalysis
Requires-Dist: cdsapi; extra == "reanalysis"
Requires-Dist: xarray[parallel]; extra == "reanalysis"
Requires-Dist: h5py; extra == "reanalysis"
Requires-Dist: netcdf4; extra == "reanalysis"
Provides-Extra: examples
Requires-Dist: openoa[nrel-wind,reanalysis]; extra == "examples"
Requires-Dist: jupyterlab; extra == "examples"
Provides-Extra: all
Requires-Dist: openoa[develop,docs,examples]; extra == "all"
Dynamic: license-file
